text_highlighter/__init__.py
text_highlighter/frontend/.env
text_highlighter/frontend/.prettierrc
text_highlighter/frontend/package-lock.json
text_highlighter/frontend/package.json
text_highlighter/frontend/tsconfig.json
text_highlighter/frontend/build/asset-manifest.json
text_highlighter/frontend/build/bootstrap.min.css
text_highlighter/frontend/build/index.html
text_highlighter/frontend/build/precache-manifest.f7b2543473ec69206537392d8cc01846.js
text_highlighter/frontend/build/service-worker.js
text_highlighter/frontend/build/static/css/main.dc3a666e.chunk.css
text_highlighter/frontend/build/static/css/main.dc3a666e.chunk.css.map
text_highlighter/frontend/build/static/js/2.f795d9e4.chunk.js
text_highlighter/frontend/build/static/js/2.f795d9e4.chunk.js.LICENSE.txt
text_highlighter/frontend/build/static/js/2.f795d9e4.chunk.js.map
text_highlighter/frontend/build/static/js/main.d9e3b25e.chunk.js
text_highlighter/frontend/build/static/js/main.d9e3b25e.chunk.js.map
text_highlighter/frontend/build/static/js/runtime-main.11ec9aca.js
text_highlighter/frontend/build/static/js/runtime-main.11ec9aca.js.map
text_highlighter/frontend/public/bootstrap.min.css
text_highlighter/frontend/public/index.html
text_highlighter/frontend/src/TextHighlighter.tsx
text_highlighter/frontend/src/index.tsx
text_highlighter/frontend/src/react-app-env.d.ts
text_highlighter/frontend/src/style.css
text_highlighter_hilton-0.0.16.2.dist-info/LICENSE
text_highlighter_hilton-0.0.16.2.dist-info/METADATA
text_highlighter_hilton-0.0.16.2.dist-info/WHEEL
text_highlighter_hilton-0.0.16.2.dist-info/top_level.txt
text_highlighter_hilton-0.0.16.2.dist-info/RECORD
