Metadata-Version: 2.1
Name: text-highlighter-hilton
Version: 0.0.16.2
Summary: Streamlit component for text highlighting
Home-page: https://github.com/NickHilton/text-highlighter
Author: N. Hilton
Author-email: nick.hilton@teleskope.ai
Requires-Python: >=3.6
License-File: LICENSE
Requires-Dist: streamlit>=0.63
